<ad_break>
    <advert>
        <unique_id>WPPEMMA317010</unique_id>
        <brand>Emma mattress</brand>
        <duration_seconds>10</duration_seconds>
        <last_timecode>01:57</last_timecode>
        <description>The "Emma" logo and "Easter Sale Now On" promotional text are visible in the final frames before the cut to the next advertiser.</description>
    </advert>
    <advert>
        <unique_id>SRQBSHS001030</unique_id>
        <brand>Bissell</brand>
        <duration_seconds>30</duration_seconds>
        <last_timecode>02:27</last_timecode>
        <description>The Bissell product lineup and the slogan "A New Breed of Clean" with the website URL are displayed in the concluding moments of the advertisement.</description>
    </advert>
    <advert>
        <unique_id>DAAINSU007030</unique_id>
        <brand>Insure &amp; go</brand>
        <duration_seconds>30</duration_seconds>
        <last_timecode>02:56</last_timecode>
        <description>The call to action phone number "0800 198 0198" and the "Trustworthy" rating badge are shown on screen as the ad concludes.</description>
    </advert>
    <advert>
        <unique_id>CWWGARN248020</unique_id>
        <brand>Garnier</brand>
        <last_timecode>03:17</last_timecode>
        <description>The main "GARNIER" logo accompanied by social media handles is displayed in the final frame before the ITV1 channel ident.</description>
    </advert>
</ad_break>